CHANGELOG
CONTRIBUTORS
LICENSE
MANIFEST.in
README
setup.cfg
setup.py
wrapper.py
KDVS.egg-info/PKG-INFO
KDVS.egg-info/SOURCES.txt
KDVS.egg-info/dependency_links.txt
KDVS.egg-info/top_level.txt
doc/Makefile
doc/conf.py
doc/index.rst
doc/make.bat
doc/_build/doctrees/environment.pickle
doc/_build/doctrees/index.doctree
doc/_build/doctrees/doc-api/api.doctree
doc/_build/doctrees/doc-api/kdvs.bin.doctree
doc/_build/doctrees/doc-api/kdvs.contrib.doctree
doc/_build/doctrees/doc-api/kdvs.core.doctree
doc/_build/doctrees/doc-api/kdvs.doctree
doc/_build/doctrees/doc-api/kdvs.fw.doctree
doc/_build/doctrees/doc-api/kdvs.fw.impl.annotation.doctree
doc/_build/doctrees/doc-api/kdvs.fw.impl.app.doctree
doc/_build/doctrees/doc-api/kdvs.fw.impl.data.doctree
doc/_build/doctrees/doc-api/kdvs.fw.impl.doctree
doc/_build/doctrees/doc-api/kdvs.fw.impl.envop.doctree
doc/_build/doctrees/doc-api/kdvs.fw.impl.job.doctree
doc/_build/doctrees/doc-api/kdvs.fw.impl.map.GeneID.doctree
doc/_build/doctrees/doc-api/kdvs.fw.impl.map.PKCID.doctree
doc/_build/doctrees/doc-api/kdvs.fw.impl.map.doctree
doc/_build/doctrees/doc-api/kdvs.fw.impl.pk.doctree
doc/_build/doctrees/doc-api/kdvs.fw.impl.pk.go.doctree
doc/_build/doctrees/doc-api/kdvs.fw.impl.report.doctree
doc/_build/doctrees/doc-api/kdvs.fw.impl.stat.doctree
doc/_build/doctrees/doc-api/kdvs.tests.doctree
doc/_build/doctrees/doc-api/kdvs.tests.f.doctree
doc/_build/doctrees/doc-api/kdvs.tests.s.doctree
doc/_build/doctrees/doc-api/kdvs.tests.t.doctree
doc/_build/doctrees/doc-api/kdvs.tests.t.fw.doctree
doc/_build/doctrees/doc-api/kdvs.tests.t.fw.impl.annotation.doctree
doc/_build/doctrees/doc-api/kdvs.tests.t.fw.impl.app.doctree
doc/_build/doctrees/doc-api/kdvs.tests.t.fw.impl.data.doctree
doc/_build/doctrees/doc-api/kdvs.tests.t.fw.impl.doctree
doc/_build/doctrees/doc-api/kdvs.tests.t.fw.impl.envop.doctree
doc/_build/doctrees/doc-api/kdvs.tests.t.fw.impl.job.doctree
doc/_build/doctrees/doc-api/kdvs.tests.t.fw.impl.map.GeneID.doctree
doc/_build/doctrees/doc-api/kdvs.tests.t.fw.impl.map.PKCID.doctree
doc/_build/doctrees/doc-api/kdvs.tests.t.fw.impl.map.doctree
doc/sphinxext/numpydoc/numpydoc.egg-info/PKG-INFO
doc/sphinxext/numpydoc/numpydoc.egg-info/SOURCES.txt
doc/sphinxext/numpydoc/numpydoc.egg-info/dependency_links.txt
doc/sphinxext/numpydoc/numpydoc.egg-info/entry_points.txt
doc/sphinxext/numpydoc/numpydoc.egg-info/not-zip-safe
doc/sphinxext/numpydoc/numpydoc.egg-info/requires.txt
doc/sphinxext/numpydoc/numpydoc.egg-info/top_level.txt
