Metadata-Version: 1.1
Name: KDVS
Version: 2.0.0
Summary: 
